feems/.DS_Store
feems/__init__.py
feems/components_model/.DS_Store
feems/components_model/__init__.py
feems/components_model/component_base.py
feems/components_model/component_electric.py
feems/components_model/component_mechanical.py
feems/components_model/node.py
feems/components_model/utility.py
feems/constant.py
feems/emission.py
feems/exceptions.py
feems/fuel.py
feems/package_data/.DS_Store
feems/package_data/fuel_eu_fuel_table.csv
feems/package_data/fuel_eu_fuel_table.xlsx
feems/package_data/fuel_imo_table.csv
feems/py.typed
feems/runsimulation.py
feems/simulation_interface.py
feems/system_model.py
feems/types_for_feems.py
feems-0.11.11.dist-info/METADATA
feems-0.11.11.dist-info/WHEEL
feems-0.11.11.dist-info/licenses/LICENSE
feems-0.11.11.dist-info/RECORD
