Metadata-Version: 2.4
Name: feems
Version: 0.11.11
Summary: 
License: MIT
License-File: LICENSE
Author: Kevin Koosup Yum
Author-email: kevinkoosup.yum@sintef.no
Requires-Python: >=3.10,<3.13
Classifier: License :: OSI Approved :: MIT License
Classifier: Programming Language :: Python :: 3
Classifier: Programming Language :: Python :: 3.10
Classifier: Programming Language :: Python :: 3.11
Classifier: Programming Language :: Python :: 3.12
Requires-Dist: pandas (>=2.1.1,<3.0.0)
Requires-Dist: scipy (>=1.11.2,<2.0.0)
